specbench/__init__.py
specbench/cli.py
specbench/py.typed
specbench-0.0.1.dist-info/METADATA
specbench-0.0.1.dist-info/WHEEL
specbench-0.0.1.dist-info/entry_points.txt
specbench-0.0.1.dist-info/RECORD
