Metadata-Version: 2.4
Name: specbench
Version: 0.0.1
Summary: 化学谱学大模型 Benchmark 引擎
Author: Zhuo Yang, Tianfan Fu
Keywords: benchmark,chemistry,evaluation,spectroscopy
Requires-Python: >=3.10
Provides-Extra: dev
Requires-Dist: black>=23.0.0; extra == 'dev'
Requires-Dist: pytest>=7.4.0; extra == 'dev'
Requires-Dist: ruff>=0.1.0; extra == 'dev'
